highlightselect_model_admin/__init__.py
highlightselect_model_admin/static/highlightselect_model_admin/js/highlight_selected_rows.js
django_highlightselect_model_admin-1.0.0.dist-info/LICENCE
django_highlightselect_model_admin-1.0.0.dist-info/METADATA
django_highlightselect_model_admin-1.0.0.dist-info/WHEEL
django_highlightselect_model_admin-1.0.0.dist-info/top_level.txt
django_highlightselect_model_admin-1.0.0.dist-info/zip-safe
django_highlightselect_model_admin-1.0.0.dist-info/RECORD
